src/__init__.py
src/backtester.py
backtesterr-0.0.1.dist-info/LICENSE
backtesterr-0.0.1.dist-info/METADATA
backtesterr-0.0.1.dist-info/WHEEL
backtesterr-0.0.1.dist-info/top_level.txt
backtesterr-0.0.1.dist-info/RECORD
