Metadata-Version: 2.1
Name: backtesterr
Version: 0.0.1
Summary: Backtesterr is a lightweight Python package for backtesting trading strategies on historical data. It offers a simple API for simulating strategies, tracking performance metrics, and optimizing trading rules.
Home-page: https://github.com/jackmartin-codes/backtesterr
Author: Jack Martin
Author-email: Jack Martin <jack.martin.codes@gmail.com>
Project-URL: Homepage, https://github.com/jackmartin-codes/backtesterr
Project-URL: Issues, https://github.com/jackmartin-codes/backtesterr/issues
Classifier: Programming Language :: Python :: 3
Classifier: License :: OSI Approved :: The Unlicense (Unlicense)
Classifier: Operating System :: OS Independent
Requires-Python: >=3.8
License-File: LICENSE
